hydromt_wff/__init__.py
hydromt_wff/hydromt_wff.py
hydromt_wff-0.0.5.dist-info/METADATA
hydromt_wff-0.0.5.dist-info/WHEEL
hydromt_wff-0.0.5.dist-info/top_level.txt
hydromt_wff-0.0.5.dist-info/RECORD
