Metadata-Version: 2.1
Name: hydromt-wff
Version: 0.0.5
Summary: The package automates the pre-processing, data preparation, and set-up of Delft3D FM to simulate wadi flash floods
Home-page: UNKNOWN
Author: Aseel Moahmed
Author-email: UNKNOWN
License: UNKNOWN
Platform: UNKNOWN
